vox_django/__init__.py
vox_django/apps.py
vox_django/criptografia.py
vox_django/healthcheck/__init__.py
vox_django/healthcheck/backends.py
vox_django/management/__init__.py
vox_django/management/commands/__init__.py
vox_django/management/commands/generate_model_uml.py
vox_django/middleware.py
vox_django/models.py
vox_django/test_runner.py
vox_django/tests.py
vox_django-0.1.3.dist-info/WHEEL
vox_django-0.1.3.dist-info/METADATA
vox_django-0.1.3.dist-info/RECORD
