Metadata-Version: 2.1
Name: vox-django
Version: 0.1.3
Summary: 
Author: Jhonatan Teixeira
Author-email: jhonatan.teixeira@gmail.com
Requires-Python: >=3.8,<4.0
Classifier: Programming Language :: Python :: 3
Classifier: Programming Language :: Python :: 3.8
Classifier: Programming Language :: Python :: 3.9
Requires-Dist: django (>=3.0,<3.1)
Requires-Dist: django-cors-headers
Requires-Dist: django-health-check
Requires-Dist: django-rest-witchcraft
Requires-Dist: django-sorcery
Requires-Dist: djangorestframework (>=3.11,<3.12)
Requires-Dist: drf-yasg
Requires-Dist: pycryptodome
Requires-Dist: python-dotenv
Requires-Dist: sqlalchemy (==1.3.21)
Requires-Dist: sqlalchemy-easy-profile (>=1.2.0,<2.0.0)
Requires-Dist: sqlalchemy-pagination
Requires-Dist: sqlalchemy-schemadisplay
